actfw_gstreamer/__init__.py
actfw_gstreamer/capture.py
actfw_gstreamer/gstreamer/__init__.py
actfw_gstreamer/gstreamer/converter.py
actfw_gstreamer/gstreamer/exception.py
actfw_gstreamer/gstreamer/pipeline.py
actfw_gstreamer/gstreamer/preconfigured_pipeline.py
actfw_gstreamer/gstreamer/stream.py
actfw_gstreamer/py.typed
actfw_gstreamer/restart_handler.py
actfw_gstreamer/util.py
actfw_gstreamer-0.5.0.dist-info/LICENSE.txt
actfw_gstreamer-0.5.0.dist-info/METADATA
actfw_gstreamer-0.5.0.dist-info/WHEEL
actfw_gstreamer-0.5.0.dist-info/RECORD
