Metadata-Version: 2.3
Name: actfw-gstreamer
Version: 0.5.0
Summary: actfw's additional components using GStreamer
License: MIT
Keywords: actcast
Author: Idein Inc.
Requires-Python: >=3.9,<4.0
Classifier: Development Status :: 4 - Beta
Classifier: Intended Audience :: Developers
Classifier: License :: OSI Approved :: MIT License
Classifier: Programming Language :: Python :: 3
Classifier: Programming Language :: Python :: 3.9
Classifier: Programming Language :: Python :: 3.10
Classifier: Programming Language :: Python :: 3.11
Classifier: Programming Language :: Python :: 3.12
Classifier: Programming Language :: Python :: 3.13
Classifier: Programming Language :: Python :: 3 :: Only
Requires-Dist: Pillow (>=8,<11)
Requires-Dist: PyGObject (>=3,<4)
Requires-Dist: actfw-core (>=2.0.0,<3.0.0)
Requires-Dist: result (>=0.6.0,<0.7.0)
Project-URL: Changelog, https://github.com/Idein/actfw-gstreamer/blob/master/CHANGELOG.md
Project-URL: Documentation, https://idein.github.io/actfw-gstreamer/latest/
Project-URL: Repository, https://github.com/Idein/actfw-gstreamer
